Data_HandWrite
