Metadata-Version: 1.1
Name: Data-HandWrite
Version: 1.1.0
Summary: Hand write toolkit and data for windows
Home-page: https://pypi.org/project/Data_HandWrite
Author: KuoYuan Li
Author-email: funny4875@gmail.com
License: UNKNOWN
Keywords: machine learning,HandWrite,data
Platform: UNKNOWN
Classifier: License :: OSI Approved :: MIT License
Classifier: Programming Language :: Python :: 3.6
Classifier: Programming Language :: Python :: 3.7
Classifier: Programming Language :: Python :: 3.8
